{
	"animations": [
		{
			"offsets": [0, 0],
			"loop": false,
			"fps": 24,
			"anim": "idle",
			"indices": [],
			"name": "Idle"
		},
		{
			"offsets": [46, -12],
			"loop": false,
			"fps": 24,
			"anim": "singLEFT",
			"indices": [],
			"name": "Left"
		},
		{
			"offsets": [-62, -95],
			"loop": false,
			"fps": 24,
			"anim": "singDOWN",
			"indices": [],
			"name": "Down"
		},
		{
			"offsets": [-29, 35],
			"loop": false,
			"fps": 24,
			"anim": "singUP",
			"indices": [],
			"name": "Up"
		},
		{
			"offsets": [-110, -20],
			"loop": false,
			"fps": 24,
			"anim": "singRIGHT",
			"indices": [],
			"name": "Right"
		}
	],
	"vocals_file": "",
	"no_antialiasing": false,
	"image": "characters/Mouse_2_Remake",
	"position": [-50, 110],
	"healthicon": "mouse-2",
	"flip_x": false,
	"healthbar_colors": [58, 65, 88],
	"camera_position": [0, 130],
	"sing_duration": 4,
	"scale": 1,
	"_editor_isPlayer": false
}